shiny_querynav/__init__.py
shiny_querynav/querynav.py
shiny_querynav/www/shiny_querynav.js
shiny_querynav-0.1.0.dist-info/METADATA
shiny_querynav-0.1.0.dist-info/WHEEL
shiny_querynav-0.1.0.dist-info/licenses/LICENSE
shiny_querynav-0.1.0.dist-info/RECORD
