Metadata-Version: 2.4
Name: shiny-querynav
Version: 0.1.0
Summary: A Py Shiny extension that synchronizes navigation components with URL search parameters
Project-URL: Homepage, https://github.com/kenjisato/shiny-querynav
Project-URL: Repository, https://github.com/kenjisato/shiny-querynav
Project-URL: Issues, https://github.com/kenjisato/shiny-querynav/issues
Author-email: Kenji Sato <mail@kenjisato.jp>
License: MIT
License-File: LICENSE
Keywords: bookmarkable,navigation,query-parameters,shiny,url
Classifier: Development Status :: 4 - Beta
Classifier: Intended Audience :: Developers
Classifier: License :: OSI Approved :: MIT License
Classifier: Programming Language :: Python :: 3
Classifier: Programming Language :: Python :: 3 :: Only
Classifier: Programming Language :: Python :: 3.12
Classifier: Topic :: Internet :: WWW/HTTP :: Dynamic Content
Classifier: Topic :: Software Development :: Libraries :: Python Modules
Requires-Python: >=3.12
Requires-Dist: shiny>=1.5.0
